pyqt5filedialogs/__init__.py
pyqt5filedialogs/_filedialog.py
qt5filedialog/__init__.py
qt5filedialog/_filedialog.py
pyqt5_file_dialogs-1.0.1.dist-info/LICENSE.txt
pyqt5_file_dialogs-1.0.1.dist-info/METADATA
pyqt5_file_dialogs-1.0.1.dist-info/WHEEL
pyqt5_file_dialogs-1.0.1.dist-info/top_level.txt
pyqt5_file_dialogs-1.0.1.dist-info/RECORD
