Metadata-Version: 2.1
Name: pyqt5-file-dialogs
Version: 1.0.1
Summary: Interactive file selection prompts using Qt5.
Home-page: https://github.com/timothypettingill/pyqt5-file-dialogs
Author: Timothy Pettingill
Author-email: tpettingill@outlook.com
License: UNKNOWN
Platform: UNKNOWN
Classifier: Development Status :: 5 - Production/Stable
Classifier: License :: OSI Approved :: MIT License
Classifier: Operating System :: OS Independent
Classifier: Intended Audience :: Developers
Classifier: Programming Language :: Python :: 3
Classifier: Programming Language :: Python :: 3.6
Classifier: Programming Language :: Python :: 3.7
Classifier: Programming Language :: Python :: 3.8
Classifier: Programming Language :: Python :: 3 :: Only
Requires-Python: >=3.6
Requires-Dist: PySide2
